css/__init__.py
pycss-0.0.2.dist-info/LICENCE
pycss-0.0.2.dist-info/METADATA
pycss-0.0.2.dist-info/WHEEL
pycss-0.0.2.dist-info/top_level.txt
pycss-0.0.2.dist-info/RECORD
