Metadata-Version: 2.1
Name: pycss
Version: 0.0.2
Summary: A package that will help you to color your output!
Home-page: https://github.com/Ayaan-Imran/pycss
Author: Ayaan Imran
Author-email: miskiacuberayaan2509@gmail.com
Classifier: Programming Language :: Python :: 3
Classifier: License :: OSI Approved :: MIT License
Classifier: Operating System :: OS Independent
Requires-Python: >=3.6
License-File: LICENCE
